cognihive/__init__.py
cognihive/cli.py
cognihive/access/__init__.py
cognihive/consensus/__init__.py
cognihive/core/__init__.py
cognihive/core/agent_registry.py
cognihive/core/hive.py
cognihive/core/memory_types.py
cognihive/integrations/__init__.py
cognihive/integrations/autogen.py
cognihive/integrations/crewai.py
cognihive/integrations/langchain.py
cognihive/integrations/langgraph.py
cognihive/integrations/mcp.py
cognihive/integrations/openai.py
cognihive/memory/__init__.py
cognihive/storage/__init__.py
cognihive/storage/base.py
cognihive/storage/chroma.py
cognihive/transactive/__init__.py
cognihive/transactive/expertise_index.py
cognihive/transactive/expertise_router.py
cognihive-0.1.3.dist-info/METADATA
cognihive-0.1.3.dist-info/WHEEL
cognihive-0.1.3.dist-info/entry_points.txt
cognihive-0.1.3.dist-info/licenses/LICENSE
cognihive-0.1.3.dist-info/RECORD
