Metadata-Version: 2.4
Name: cognihive
Version: 0.1.3
Summary: The World's First Transactive Memory System for Multi-Agent AI - Gives your agent team a collective mind
Project-URL: Homepage, https://github.com/vmore2/CogniHive
Project-URL: Documentation, https://github.com/vmore2/CogniHive#readme
Project-URL: Repository, https://github.com/vmore2/CogniHive
Project-URL: Issues, https://github.com/vmore2/CogniHive/issues
Author-email: Vrushket <vrushket2604@gmail.com>
License: MIT
License-File: LICENSE
Keywords: agents,ai,autogen,collective-intelligence,crewai,langgraph,llm,memory,multi-agent,rag,transactive-memory
Classifier: Development Status :: 4 - Beta
Classifier: Intended Audience :: Developers
Classifier: License :: OSI Approved :: MIT License
Classifier: Programming Language :: Python :: 3
Classifier: Programming Language :: Python :: 3.9
Classifier: Programming Language :: Python :: 3.10
Classifier: Programming Language :: Python :: 3.11
Classifier: Programming Language :: Python :: 3.12
Classifier: Topic :: Scientific/Engineering :: Artificial Intelligence
Requires-Python: >=3.9
Requires-Dist: chromadb>=0.4.0
Requires-Dist: numpy>=1.24.0
Requires-Dist: pydantic>=2.0.0
Requires-Dist: rich>=13.0.0
Requires-Dist: sentence-transformers>=2.2.0
Provides-Extra: all
Requires-Dist: crewai>=0.30.0; extra == 'all'
Requires-Dist: langchain-core>=0.1.0; extra == 'all'
Requires-Dist: langchain>=0.1.0; extra == 'all'
Requires-Dist: langgraph>=0.0.30; extra == 'all'
Requires-Dist: mcp>=0.1.0; extra == 'all'
Requires-Dist: openai>=1.0.0; extra == 'all'
Requires-Dist: pyautogen>=0.2.0; extra == 'all'
Provides-Extra: autogen
Requires-Dist: pyautogen>=0.2.0; extra == 'autogen'
Provides-Extra: crewai
Requires-Dist: crewai>=0.30.0; extra == 'crewai'
Provides-Extra: dev
Requires-Dist: black>=23.0.0; extra == 'dev'
Requires-Dist: mypy>=1.0.0; extra == 'dev'
Requires-Dist: pytest-asyncio>=0.21.0; extra == 'dev'
Requires-Dist: pytest-cov>=4.0.0; extra == 'dev'
Requires-Dist: pytest>=7.0.0; extra == 'dev'
Requires-Dist: ruff>=0.1.0; extra == 'dev'
Provides-Extra: langchain
Requires-Dist: langchain-core>=0.1.0; extra == 'langchain'
Requires-Dist: langchain>=0.1.0; extra == 'langchain'
Provides-Extra: langgraph
Requires-Dist: langgraph>=0.0.30; extra == 'langgraph'
Provides-Extra: mcp
Requires-Dist: mcp>=0.1.0; extra == 'mcp'
Provides-Extra: openai
Requires-Dist: openai>=1.0.0; extra == 'openai'
